CHANGES.txt
LICENSE.txt
MANIFEST.in
README.rst
ankiserverctl.py
example.ini
logging.conf
setup.py
supervisor-anki-server.conf
AnkiServer/__init__.py
AnkiServer/collection.py
AnkiServer/find.py
AnkiServer/importer.py
AnkiServer/logpatch.py
AnkiServer/threading.py
AnkiServer/utils.py
AnkiServer.egg-info/PKG-INFO
AnkiServer.egg-info/SOURCES.txt
AnkiServer.egg-info/dependency_links.txt
AnkiServer.egg-info/entry_points.txt
AnkiServer.egg-info/not-zip-safe
AnkiServer.egg-info/requires.txt
AnkiServer.egg-info/top_level.txt
AnkiServer/apps/__init__.py
AnkiServer/apps/rest_app.py
AnkiServer/apps/sync_app.py
anki-bundled/.git
anki-bundled/.gitignore
anki-bundled/LICENSE
anki-bundled/LICENSE.logo
anki-bundled/Makefile
anki-bundled/README
anki-bundled/README.development
anki-bundled/anki.1
anki-bundled/anki.bat
anki-bundled/anki.desktop
anki-bundled/anki.png
anki-bundled/anki.xml
anki-bundled/anki.xpm
anki-bundled/runanki
anki-bundled/anki/__init__.py
anki-bundled/anki/anki
anki-bundled/anki/ankiweb.certs
anki-bundled/anki/cards.py
anki-bundled/anki/collection.py
anki-bundled/anki/consts.py
anki-bundled/anki/db.py
anki-bundled/anki/decks.py
anki-bundled/anki/errors.py
anki-bundled/anki/exporting.py
anki-bundled/anki/find.py
anki-bundled/anki/hooks.py
anki-bundled/anki/js.py
anki-bundled/anki/lang.py
anki-bundled/anki/latex.py
anki-bundled/anki/media.py
anki-bundled/anki/models.py
anki-bundled/anki/notes.py
anki-bundled/anki/sched.py
anki-bundled/anki/sound.py
anki-bundled/anki/stats.py
anki-bundled/anki/statsbg.py
anki-bundled/anki/stdmodels.py
anki-bundled/anki/storage.py
anki-bundled/anki/sync.py
anki-bundled/anki/tags.py
anki-bundled/anki/upgrade.py
anki-bundled/anki/utils.py
anki-bundled/anki/importing/__init__.py
anki-bundled/anki/importing/anki1.py
anki-bundled/anki/importing/anki2.py
anki-bundled/anki/importing/apkg.py
anki-bundled/anki/importing/base.py
anki-bundled/anki/importing/csvfile.py
anki-bundled/anki/importing/mnemo.py
anki-bundled/anki/importing/noteimp.py
anki-bundled/anki/importing/pauker.py
anki-bundled/anki/importing/supermemo_xml.py
anki-bundled/anki/template/LICENSE
anki-bundled/anki/template/README.anki
anki-bundled/anki/template/README.rst
anki-bundled/anki/template/__init__.py
